[
  {
    "sector": "111CA/US-MN",
    "amount": 1806294705.6879
  },
  {
    "sector": "113FF/US-MN",
    "amount": 1467684.8948
  },
  {
    "sector": "211/US-MN",
    "amount": 0
  },
  {
    "sector": "212/US-MN",
    "amount": 1017319.6971
  },
  {
    "sector": "213/US-MN",
    "amount": 1718.7845
  },
  {
    "sector": "22/US-MN",
    "amount": 198721249.5535
  },
  {
    "sector": "23/US-MN",
    "amount": 0
  },
  {
    "sector": "321/US-MN",
    "amount": 256934864.9132
  },
  {
    "sector": "327/US-MN",
    "amount": 57110598.704
  },
  {
    "sector": "331/US-MN",
    "amount": 1984994.1382
  },
  {
    "sector": "332/US-MN",
    "amount": 453128653.585
  },
  {
    "sector": "333/US-MN",
    "amount": 2867609731.6227
  },
  {
    "sector": "334/US-MN",
    "amount": 2981806091.9061
  },
  {
    "sector": "335/US-MN",
    "amount": 617446522.1805
  },
  {
    "sector": "3361MV/US-MN",
    "amount": 389475539.5496
  },
  {
    "sector": "3364OT/US-MN",
    "amount": 549663554.5535
  },
  {
    "sector": "337/US-MN",
    "amount": 743747375.5309
  },
  {
    "sector": "339/US-MN",
    "amount": 4002590740.5018
  },
  {
    "sector": "311FT/US-MN",
    "amount": 7003948780.3524
  },
  {
    "sector": "313TT/US-MN",
    "amount": 100712784.0698
  },
  {
    "sector": "315AL/US-MN",
    "amount": 166358516.025
  },
  {
    "sector": "322/US-MN",
    "amount": 285523610.6383
  },
  {
    "sector": "323/US-MN",
    "amount": 216591097.5379
  },
  {
    "sector": "324/US-MN",
    "amount": 403899658.3176
  },
  {
    "sector": "325/US-MN",
    "amount": 571009188.4591
  },
  {
    "sector": "326/US-MN",
    "amount": 313501597.3215
  },
  {
    "sector": "42/US-MN",
    "amount": 15867330922.106
  },
  {
    "sector": "441/US-MN",
    "amount": 0
  },
  {
    "sector": "445/US-MN",
    "amount": 0
  },
  {
    "sector": "452/US-MN",
    "amount": 0
  },
  {
    "sector": "4A0/US-MN",
    "amount": 2386036914.6313
  },
  {
    "sector": "481/US-MN",
    "amount": 1112049439.4525
  },
  {
    "sector": "482/US-MN",
    "amount": 136096662.2804
  },
  {
    "sector": "483/US-MN",
    "amount": 390596.5197
  },
  {
    "sector": "484/US-MN",
    "amount": 1151186842.6238
  },
  {
    "sector": "485/US-MN",
    "amount": 0
  },
  {
    "sector": "486/US-MN",
    "amount": 10915043.6432
  },
  {
    "sector": "487OS/US-MN",
    "amount": 0
  },
  {
    "sector": "493/US-MN",
    "amount": 14101.2996
  },
  {
    "sector": "511/US-MN",
    "amount": 3158285426.7376
  },
  {
    "sector": "512/US-MN",
    "amount": 97402348.6723
  },
  {
    "sector": "513/US-MN",
    "amount": 41661384.5246
  },
  {
    "sector": "514/US-MN",
    "amount": 1284621.4298
  },
  {
    "sector": "521CI/US-MN",
    "amount": 5325746092.4349
  },
  {
    "sector": "523/US-MN",
    "amount": 9146529.8714
  },
  {
    "sector": "524/US-MN",
    "amount": 8920245214.3938
  },
  {
    "sector": "525/US-MN",
    "amount": 835695755.6118
  },
  {
    "sector": "HS/US-MN",
    "amount": 0
  },
  {
    "sector": "ORE/US-MN",
    "amount": 0
  },
  {
    "sector": "532RL/US-MN",
    "amount": 230427663.4343
  },
  {
    "sector": "5411/US-MN",
    "amount": 311558324.1435
  },
  {
    "sector": "5415/US-MN",
    "amount": 946037070.6254
  },
  {
    "sector": "5412OP/US-MN",
    "amount": 9220519833.1336
  },
  {
    "sector": "55/US-MN",
    "amount": 0
  },
  {
    "sector": "561/US-MN",
    "amount": 246522717.0516
  },
  {
    "sector": "562/US-MN",
    "amount": 378157430.1092
  },
  {
    "sector": "61/US-MN",
    "amount": 3568161951.627
  },
  {
    "sector": "621/US-MN",
    "amount": 0
  },
  {
    "sector": "622/US-MN",
    "amount": 0
  },
  {
    "sector": "623/US-MN",
    "amount": 0
  },
  {
    "sector": "624/US-MN",
    "amount": 0
  },
  {
    "sector": "711AS/US-MN",
    "amount": 229367387.7243
  },
  {
    "sector": "713/US-MN",
    "amount": 1372587107.8659
  },
  {
    "sector": "721/US-MN",
    "amount": 2706242.9446
  },
  {
    "sector": "722/US-MN",
    "amount": 0
  },
  {
    "sector": "81/US-MN",
    "amount": 89469983.7227
  },
  {
    "sector": "GFGD/US-MN",
    "amount": 0
  },
  {
    "sector": "GFGN/US-MN",
    "amount": 0
  },
  {
    "sector": "GFE/US-MN",
    "amount": 108008339.1709
  },
  {
    "sector": "GSLG/US-MN",
    "amount": 0
  },
  {
    "sector": "GSLE/US-MN",
    "amount": 0
  },
  {
    "sector": "Used/US-MN",
    "amount": 0
  },
  {
    "sector": "Other/US-MN",
    "amount": 0
  },
  {
    "sector": "111CA/RoUS",
    "amount": 66382003964.2939
  },
  {
    "sector": "113FF/RoUS",
    "amount": 5512625854.9543
  },
  {
    "sector": "211/RoUS",
    "amount": 0
  },
  {
    "sector": "212/RoUS",
    "amount": 48649047.1954
  },
  {
    "sector": "213/RoUS",
    "amount": 76508255072.8502
  },
  {
    "sector": "22/RoUS",
    "amount": 282008499157.591
  },
  {
    "sector": "23/RoUS",
    "amount": 1517136735805.53
  },
  {
    "sector": "321/RoUS",
    "amount": 11413408784.8335
  },
  {
    "sector": "327/RoUS",
    "amount": 6672117448.6957
  },
  {
    "sector": "331/RoUS",
    "amount": 431085796.8997
  },
  {
    "sector": "332/RoUS",
    "amount": 19981827351.331
  },
  {
    "sector": "333/RoUS",
    "amount": 154668052257.473
  },
  {
    "sector": "334/RoUS",
    "amount": 111224841363.824
  },
  {
    "sector": "335/RoUS",
    "amount": 44688437412.442
  },
  {
    "sector": "3361MV/RoUS",
    "amount": 331744270192.287
  },
  {
    "sector": "3364OT/RoUS",
    "amount": 89664955912.7009
  },
  {
    "sector": "337/RoUS",
    "amount": 40946840744.9448
  },
  {
    "sector": "339/RoUS",
    "amount": 86269428675.7621
  },
  {
    "sector": "311FT/RoUS",
    "amount": 607642735045.419
  },
  {
    "sector": "313TT/RoUS",
    "amount": 13640837067.5127
  },
  {
    "sector": "315AL/RoUS",
    "amount": 14911203087.0211
  },
  {
    "sector": "322/RoUS",
    "amount": 19983698943.3882
  },
  {
    "sector": "323/RoUS",
    "amount": 4717837978.6163
  },
  {
    "sector": "324/RoUS",
    "amount": 97584228893.6586
  },
  {
    "sector": "325/RoUS",
    "amount": 222387484654.983
  },
  {
    "sector": "326/RoUS",
    "amount": 22389370878.4896
  },
  {
    "sector": "42/RoUS",
    "amount": 886902849097.969
  },
  {
    "sector": "441/RoUS",
    "amount": 204271124263.874
  },
  {
    "sector": "445/RoUS",
    "amount": 245080783716.275
  },
  {
    "sector": "452/RoUS",
    "amount": 230628239293.531
  },
  {
    "sector": "4A0/RoUS",
    "amount": 928432896152.899
  },
  {
    "sector": "481/RoUS",
    "amount": 54413810041.7312
  },
  {
    "sector": "482/RoUS",
    "amount": 11614233827.3625
  },
  {
    "sector": "483/RoUS",
    "amount": 13759977079.6754
  },
  {
    "sector": "484/RoUS",
    "amount": 125570745846.6
  },
  {
    "sector": "485/RoUS",
    "amount": 26930028822.8245
  },
  {
    "sector": "486/RoUS",
    "amount": 2594830428.1115
  },
  {
    "sector": "487OS/RoUS",
    "amount": 26307106276.4683
  },
  {
    "sector": "493/RoUS",
    "amount": 90264602.0101
  },
  {
    "sector": "511/RoUS",
    "amount": 254966657938.203
  },
  {
    "sector": "512/RoUS",
    "amount": 52165322388.549
  },
  {
    "sector": "513/RoUS",
    "amount": 371499658285.245
  },
  {
    "sector": "514/RoUS",
    "amount": 113672512553.582
  },
  {
    "sector": "521CI/RoUS",
    "amount": 292390906260.98
  },
  {
    "sector": "523/RoUS",
    "amount": 265363009684.753
  },
  {
    "sector": "524/RoUS",
    "amount": 430872457958.671
  },
  {
    "sector": "525/RoUS",
    "amount": 165101454002.263
  },
  {
    "sector": "HS/RoUS",
    "amount": 2263321594978.7
  },
  {
    "sector": "ORE/RoUS",
    "amount": 187922422034.887
  },
  {
    "sector": "532RL/RoUS",
    "amount": 109151053008.513
  },
  {
    "sector": "5411/RoUS",
    "amount": 136639272016.121
  },
  {
    "sector": "5415/RoUS",
    "amount": 301729548657.409
  },
  {
    "sector": "5412OP/RoUS",
    "amount": 764103479536.675
  },
  {
    "sector": "55/RoUS",
    "amount": 0
  },
  {
    "sector": "561/RoUS",
    "amount": 52007183274.6876
  },
  {
    "sector": "562/RoUS",
    "amount": 29034055334.0298
  },
  {
    "sector": "61/RoUS",
    "amount": 346002752746.462
  },
  {
    "sector": "621/RoUS",
    "amount": 1064726642517.19
  },
  {
    "sector": "622/RoUS",
    "amount": 1118344210281.62
  },
  {
    "sector": "623/RoUS",
    "amount": 248382651792.374
  },
  {
    "sector": "624/RoUS",
    "amount": 229052841706.456
  },
  {
    "sector": "711AS/RoUS",
    "amount": 43510091888.2606
  },
  {
    "sector": "713/RoUS",
    "amount": 134841687024.692
  },
  {
    "sector": "721/RoUS",
    "amount": 84840807794.3413
  },
  {
    "sector": "722/RoUS",
    "amount": 688872003499.54
  },
  {
    "sector": "81/RoUS",
    "amount": 587661196301.614
  },
  {
    "sector": "GFGD/RoUS",
    "amount": 697473297297.881
  },
  {
    "sector": "GFGN/RoUS",
    "amount": 456714341548.932
  },
  {
    "sector": "GFE/RoUS",
    "amount": 18030160704.0461
  },
  {
    "sector": "GSLG/RoUS",
    "amount": 1882400903684.4
  },
  {
    "sector": "GSLE/RoUS",
    "amount": 72140018284.4466
  },
  {
    "sector": "Used/RoUS",
    "amount": -40486023851.2634
  },
  {
    "sector": "Other/RoUS",
    "amount": -75255930664.672
  }
]
